[
    {
        "slug": "main",
        "title": "Chained Up Scarlet",
        "description": "Contains a translation for 18trip's Ev3ns Main Story!",
        "type": "Main Story",
        "chapters": 47,
        "cover": "file/reitoouji/ro_NzdCaB66aae0f9i6.webp?timestamp=1722474749507",
        "position": "55%"
    },
    {
        "slug": "kuguri_novel",
        "title": "S.139, R.2B",
        "description": "Contains a translation for Domeki Kuguri's Novel!",
        "type": "Novel",
        "chapters": 5,
        "cover": "file/reitoouji/ro_9daEM166aae661Z6.webp?timestamp=1722476138765",
        "position": "55%"
    },
    {
        "slug": "ayakashi_parade",
        "title": "Ayakashi Parade in mahorova",
        "description": "HAMA Tours received a request for individuals to participate in a cosplay event in mahorova. The team selected to participate consisted of Kuguri, Nanaki, Kinari, Nagi, and Ushio. However, the group faces unexpected creative differences while presenting cosplay ideas...",
        "type": "Event Story",
        "chapters": 9,
        "cover": "file/reitoouji/ro_e64w1K66aadf2eu6.webp?timestamp=1722474290102",
        "position": "55% 7%"
    }
]
